check_type/__init__.py
check_type/check_type.py
check_type-0.0.2.dist-info/LICENSE
check_type-0.0.2.dist-info/METADATA
check_type-0.0.2.dist-info/WHEEL
check_type-0.0.2.dist-info/top_level.txt
check_type-0.0.2.dist-info/RECORD
